custos/__init__.py
custos/enums.py
custos/errors.py
custos/transformer.py
custos/execution/__init__.py
custos/execution/base.py
custos/execution/pandas_exec.py
custos/planning/__init__.py
custos/planning/plan.py
custos/planning/planner.py
custos/planning/steps.py
custos/policy/__init__.py
custos/policy/loader.py
custos/policy/model.py
custos/report/__init__.py
custos/report/models.py
custos_guardrails-0.1.1.dist-info/licenses/LICENSE
custos_guardrails-0.1.1.dist-info/METADATA
custos_guardrails-0.1.1.dist-info/WHEEL
custos_guardrails-0.1.1.dist-info/top_level.txt
custos_guardrails-0.1.1.dist-info/RECORD
