Metadata-Version: 2.4
Name: custos-guardrails
Version: 0.1.1
Summary: Policy-driven guardrails for common data transformations
Author: Okeino McGowan
License: MIT License
Project-URL: Homepage, https://github.com/okeino/custos
Project-URL: Repository, https://github.com/okeino/custos
Project-URL: Issues, https://github.com/okeino/custos/issues
Keywords: data-engineering,data-quality,data-transformation,policy-as-code,etl
Classifier: Development Status :: 3 - Alpha
Classifier: Intended Audience :: Developers
Classifier: Intended Audience :: Information Technology
Classifier: Topic :: Software Development :: Libraries
Classifier: Topic :: Database
Classifier: Topic :: Scientific/Engineering
Classifier: License :: OSI Approved :: MIT License
Classifier: Programming Language :: Python :: 3
Classifier: Programming Language :: Python :: 3.9
Classifier: Programming Language :: Python :: 3.10
Classifier: Programming Language :: Python :: 3.11
Requires-Python: >=3.9
License-File: LICENSE
Requires-Dist: pandas>=1.5
Requires-Dist: pyyaml>=6.0
Provides-Extra: polars
Requires-Dist: polars>=0.20; extra == "polars"
Provides-Extra: spark
Requires-Dist: pyspark>=3.5; extra == "spark"
Provides-Extra: dev
Requires-Dist: pytest>=7.0; extra == "dev"
Requires-Dist: pytest-cov; extra == "dev"
Requires-Dist: black; extra == "dev"
Requires-Dist: ruff; extra == "dev"
Requires-Dist: mypy; extra == "dev"
Dynamic: license-file
